NHXCrypt/NHXCrypt.py
NHXCrypt/__init__.py
NHXCrypt-1.2.1.dist-info/LICENSE
NHXCrypt-1.2.1.dist-info/METADATA
NHXCrypt-1.2.1.dist-info/WHEEL
NHXCrypt-1.2.1.dist-info/top_level.txt
NHXCrypt-1.2.1.dist-info/RECORD
