Metadata-Version: 2.1
Name: NHXCrypt
Version: 1.2.1
Summary: NHXCrypt is a module that uses NHXCrypt--8-128 Algorithms to encrypt and decrypt the files using a single key with a 'mathless' cryptography technique.
Home-page: https://github.com/chmuhammadsohaib/NHXCrypt
Author: NHXTech
Author-email: chmuhammadsohaib@gmail.com
License: MIT
Keywords: NHXCrypt NHX NHXTech chmuhammadsohaib Cryptography
Platform: UNKNOWN
Classifier: Development Status :: 5 - Production/Stable
Classifier: Intended Audience :: Developers
Classifier: Topic :: Software Development :: Build Tools
Classifier: Programming Language :: Python :: 3
Classifier: License :: OSI Approved :: MIT License
Classifier: Operating System :: OS Independent
Requires-Python: >=3
